setup.cfg
setup.py
simple_redis_conn/__init__.py
simple_redis_conn/redis_conn.py
simple_redis_conn.egg-info/PKG-INFO
simple_redis_conn.egg-info/SOURCES.txt
simple_redis_conn.egg-info/dependency_links.txt
simple_redis_conn.egg-info/requires.txt
simple_redis_conn.egg-info/top_level.txt