Metadata-Version: 1.1
Name: simple-redis-conn
Version: 0.0.2
Summary: Mapping operators to a dictionary switch
Home-page: https://github.com/tekton/simple_redis_conn_python
Author: Tyler Agee
Author-email: tyler@pyroturtle.com
License: MIT License
Keywords: operator
Platform: UNKNOWN
Classifier: Development Status :: 4 - Beta
Classifier: Intended Audience :: Developers
Classifier: License :: OSI Approved :: MIT License
Classifier: Programming Language :: Python
Classifier: Programming Language :: Python :: 2.7
Classifier: Topic :: Software Development :: Libraries :: Python Modules
